smartbee/__init__.py
smartbee/smartbee.py
smartbee_rhanielmx-0.1.4.dist-info/LICENSE
smartbee_rhanielmx-0.1.4.dist-info/METADATA
smartbee_rhanielmx-0.1.4.dist-info/WHEEL
smartbee_rhanielmx-0.1.4.dist-info/top_level.txt
smartbee_rhanielmx-0.1.4.dist-info/RECORD
